build/lib/build/lib/build/lib/build/lib/build/lib/build/lib/build/lib/build/lib/numbers_and_brightness/__init__.py
build/lib/build/lib/build/lib/build/lib/build/lib/build/lib/build/lib/build/lib/numbers_and_brightness/__main__.py
build/lib/build/lib/build/lib/build/lib/build/lib/build/lib/build/lib/build/lib/numbers_and_brightness/_defaults.py
build/lib/build/lib/build/lib/build/lib/build/lib/build/lib/build/lib/build/lib/numbers_and_brightness/analysis.py
build/lib/build/lib/build/lib/build/lib/build/lib/build/lib/build/lib/build/lib/numbers_and_brightness/cli.py
build/lib/build/lib/build/lib/build/lib/build/lib/build/lib/build/lib/build/lib/numbers_and_brightness/gui.py
build/lib/build/lib/build/lib/build/lib/build/lib/build/lib/build/lib/build/lib/numbers_and_brightness/_gui_components/__init__.py
build/lib/build/lib/build/lib/build/lib/build/lib/build/lib/build/lib/build/lib/numbers_and_brightness/_gui_components/_brightness_intensity.py
build/lib/build/lib/build/lib/build/lib/build/lib/build/lib/build/lib/build/lib/numbers_and_brightness/_gui_components/_utils.py
build/lib/build/lib/build/lib/build/lib/build/lib/build/lib/build/lib/numbers_and_brightness/__init__.py
build/lib/build/lib/build/lib/build/lib/build/lib/build/lib/build/lib/numbers_and_brightness/__main__.py
build/lib/build/lib/build/lib/build/lib/build/lib/build/lib/build/lib/numbers_and_brightness/_defaults.py
build/lib/build/lib/build/lib/build/lib/build/lib/build/lib/build/lib/numbers_and_brightness/analysis.py
build/lib/build/lib/build/lib/build/lib/build/lib/build/lib/build/lib/numbers_and_brightness/cli.py
build/lib/build/lib/build/lib/build/lib/build/lib/build/lib/build/lib/numbers_and_brightness/gui.py
build/lib/build/lib/build/lib/build/lib/build/lib/build/lib/build/lib/numbers_and_brightness/_gui_components/__init__.py
build/lib/build/lib/build/lib/build/lib/build/lib/build/lib/build/lib/numbers_and_brightness/_gui_components/_brightness_intensity.py
numbers_and_brightness-0.1.13.dist-info/licenses/LICENSE
numbers_and_brightness-0.1.13.dist-info/METADATA
numbers_and_brightness-0.1.13.dist-info/WHEEL
numbers_and_brightness-0.1.13.dist-info/entry_points.txt
numbers_and_brightness-0.1.13.dist-info/top_level.txt
numbers_and_brightness-0.1.13.dist-info/RECORD
