Metadata-Version: 2.4
Name: numbers_and_brightness
Version: 0.1.13
Summary: Numbers and brightness analysis for microscopic image analysis implemented in python.
Author: KJ van Beem
License: GPL-3.0
Project-URL: Homepage, https://github.com/JvB22/Numbers_and_brightness
Classifier: Programming Language :: Python :: 3
Classifier: Operating System :: OS Independent
Requires-Python: <3.13,>=3.8
License-File: LICENSE
Requires-Dist: cellpose[gui]==3.1.1.2
Requires-Dist: numpy==2.0.2
Requires-Dist: matplotlib>=3.10.1
Requires-Dist: opencv-python>=4.11.0.86
Requires-Dist: scipy>=1.15.2
Requires-Dist: tifffile>=2025.3.30
Requires-Dist: tqdm>=4.67.1
Requires-Dist: pyshortcuts>=1.9.5
Requires-Dist: PyQt6>=6.9.0
Requires-Dist: pandas>=2.2.3
Dynamic: license-file
